{"defaultTheme":"dark","project":{"project_id":"cae73283-c711-409b-8ef0-50c8b3c14516","project_name":"c2","project_description":null,"owner_user_id":1,"created_datetime":"2024-02-21T18:48:28.676Z","edited_datetime":"2024-02-22T14:55:14.933Z"},"elements":[{"_id":"db991fa8-e384-4cae-9fab-ab2e39c7ab1b","_userID":null,"_parentId":null,"_content":null,"_type":"div","_disableDelete":true,"_page":"index","props":{},"attributes":{"style":{"height":"100%"}}},{"_id":"1f164b30-cbe4-4b8f-87e5-7d304620e8d8","_userID":null,"_parentId":null,"_content":null,"_type":"div","_disableDelete":true,"_page":"page2","props":{},"attributes":{"style":{"height":"100%"}}},{"type":"Typography","props":{"children":"Page2","align":"inherit","variant":"h1","color":"secondary"},"icon":"M18.5,4L19.66,8.35L18.7,8.61C18.25,7.74 17.79,6.87 17.26,6.43C16.73,6 16.11,6 15.5,6H13V16.5C13,17 13,17.5 13.33,17.75C13.67,18 14.33,18 15,18V19H9V18C9.67,18 10.33,18 10.67,17.75C11,17.5 11,17 11,16.5V6H8.5C7.89,6 7.27,6 6.74,6.43C6.21,6.87 5.75,7.74 5.3,8.61L4.34,8.35L5.5,4H18.5Z","category":"basic","schema":{"type":"object","required":true,"properties":{"children":{"type":"string","form":{"defaultValue":"Test Typography"}},"noWrap":{"type":"boolean","form":{"defaultValue":false}},"align":{"type":"string","enum":["inherit","left","center","right","justify"],"form":{"defaultValue":"inherit"}},"variant":{"type":"string","enum":["h1","h2","h3","h4","h5","h6","body1","body2","subtitle1","subtitle2","caption","button","overline","inherit"],"form":{"defaultValue":"body1"}},"color":{"type":"string","enum":["primary","secondary","error","warning.main","info.main","success.main","text.primary","text.secondary","text.disabled","text.hint","divider","action.active","inherit"]}}},"_id":"767b98bd-0f28-4764-9cd3-66680a1379f0","_userID":null,"_parentId":"1f164b30-cbe4-4b8f-87e5-7d304620e8d8","_content":null,"_type":"Typography","_page":"page2","attributes":{}},{"type":"Typography","props":{"children":"INDEX ","align":"inherit","variant":"h1","color":"primary"},"icon":"M18.5,4L19.66,8.35L18.7,8.61C18.25,7.74 17.79,6.87 17.26,6.43C16.73,6 16.11,6 15.5,6H13V16.5C13,17 13,17.5 13.33,17.75C13.67,18 14.33,18 15,18V19H9V18C9.67,18 10.33,18 10.67,17.75C11,17.5 11,17 11,16.5V6H8.5C7.89,6 7.27,6 6.74,6.43C6.21,6.87 5.75,7.74 5.3,8.61L4.34,8.35L5.5,4H18.5Z","category":"basic","schema":{"type":"object","required":true,"properties":{"children":{"type":"string","form":{"defaultValue":"Test Typography"}},"noWrap":{"type":"boolean","form":{"defaultValue":false}},"align":{"type":"string","enum":["inherit","left","center","right","justify"],"form":{"defaultValue":"inherit"}},"variant":{"type":"string","enum":["h1","h2","h3","h4","h5","h6","body1","body2","subtitle1","subtitle2","caption","button","overline","inherit"],"form":{"defaultValue":"body1"}},"color":{"type":"string","enum":["primary","secondary","error","warning.main","info.main","success.main","text.primary","text.secondary","text.disabled","text.hint","divider","action.active","inherit"]}}},"_id":"5d6823cf-ee30-4fd3-8d01-de22e00bd1cb","_userID":null,"_parentId":"db991fa8-e384-4cae-9fab-ab2e39c7ab1b","_content":null,"_type":"Typography","_page":"index","attributes":{}},{"_id":"c630c81f-f398-4a12-9b98-0e6f14fad5a4","_userID":null,"_parentId":"db991fa8-e384-4cae-9fab-ab2e39c7ab1b","_content":"-> to Page 2","_type":"a","_page":"index","props":{},"attributes":{"href":"/page2"}},{"_id":"dd2f0e49-bc4f-4e2d-b6ee-c61d472fc91b","_userID":null,"_parentId":"db991fa8-e384-4cae-9fab-ab2e39c7ab1b","_content":null,"_type":"img","_page":"index","props":{},"attributes":{"src":"/testapp/assets/images/4f6390fe-9711-40b6-a245-69efa635dbee.jpg","style":{"width":"320px","display":"block"}}},{"_id":"a1ea3bb1-8154-4057-9819-a24be0f6ecc9","_userID":null,"_parentId":"1f164b30-cbe4-4b8f-87e5-7d304620e8d8","_content":null,"_type":"img","_page":"page2","props":{},"attributes":{"src":"/testapp/assets/images/4f6390fe-9711-40b6-a245-69efa635dbee.jpg","style":{"width":"34%"}}}],"cssSelectors":[],"assets":{"images":[{"_id":"4f6390fe-9711-40b6-a245-69efa635dbee","fileName":"IMG_20200624_153317.jpg","created_datetime":null,"edited_datetime":null}]},"theme":{},"themes":[{"id":"fb9e3978-0a0f-4361-bd7a-ddd3bbfd6bd7","project_id":"cae73283-c711-409b-8ef0-50c8b3c14516","name":"light","mode":"light","primary_main":"#009688","primary_light":"rgb(51, 171, 159)","primary_dark":"rgb(0, 105, 95)","primary_contrasttext":"#fff","secondary_main":"#f50057","secondary_light":"rgb(247, 51, 120)","secondary_dark":"rgb(171, 0, 60)","secondary_contrasttext":"#fff","error_main":"#d32f2f","error_light":"#ef5350","error_dark":"#c62828","error_contrasttext":"#fff","warning_main":"#ed6c02","warning_light":"#ff9800","warning_dark":"#e65100","warning_contrasttext":"#fff","info_main":"#0288d1","info_light":"#03a9f4","info_dark":"#01579b","info_contrasttext":"#fff","success_main":"#2e7d32","success_light":"#4caf50","success_dark":"#1b5e20","success_contrasttext":"#fff","text_primary":"rgba(0, 0, 0, 0.87)","text_secondary":"rgba(0, 0, 0, 0.6)","text_disabled":"#fff","background_default":"#fff","background_paper":"#fff","action_active":"rgba(0, 0, 0, 0.54)","action_hover":"rgba(0, 0, 0, 0.04)","action_selected":"rgba(0, 0, 0, 0.08)","action_disabled":"rgba(0, 0, 0, 0.26)","action_disabled_background":"rgba(0, 0, 0, 0.12)","action_focus":"rgba(0, 0, 0, 0.12)"},{"id":"e0237054-92de-4559-a9b9-4e76e39eced4","project_id":"cae73283-c711-409b-8ef0-50c8b3c14516","name":"dark","mode":"dark","primary_main":"rgba(74, 144, 226, 1)","primary_light":"rgba(110, 166, 231, 1)","primary_dark":"rgba(51, 100, 158, 1)","primary_contrasttext":"#fff","secondary_main":"#f50057","secondary_light":"rgb(247, 51, 120)","secondary_dark":"rgb(171, 0, 60)","secondary_contrasttext":"#fff","error_main":"#f44336","error_light":"#e57373","error_dark":"#d32f2f","error_contrasttext":"#fff","warning_main":"#ffa726","warning_light":"#ffb74d","warning_dark":"#f57c00","warning_contrasttext":"rgba(0, 0, 0, 0.87)","info_main":"#29b6f6","info_light":"#4fc3f7","info_dark":"#0288d1","info_contrasttext":"rgba(0, 0, 0, 0.87)","success_main":"#66bb6a","success_light":"#81c784","success_dark":"#388e3c","success_contrasttext":"rgba(0, 0, 0, 0.87)","text_primary":"#fff","text_secondary":"rgba(255, 255, 255, 0.7)","text_disabled":"#333","background_default":"#333","background_paper":"#333","action_active":"#fff","action_hover":"rgba(255, 255, 255, 0.08)","action_selected":"rgba(255, 255, 255, 0.16)","action_disabled":"rgba(255, 255, 255, 0.3)","action_disabled_background":"rgba(255, 255, 255, 0.12)","action_focus":"rgba(255, 255, 255, 0.12)"}],"ui":{"previewMode":false,"pointerMode":"mixed","selected":{"page":"index","element":null,"cssSelector":null,"image":"ec9d4839-1a46-49b5-a74b-4f830565f4f2","font":null,"state":null},"detailsMenu":{"width":350,"ruleName":"","ruleValue":"","addRuleName":"","addRuleValue":"","htmlElement":{"editCssRuleName":null,"editCssRuleValue":null,"cssRulesFilter":"all","activeStylesTab":"layout","classEditMode":false}},"navigationMenu":{"expandedTreeItems":[],"activeTab":"assets","elementAddComponentMode":null,"selectedTheme":null}},"fonts":["Arial, Helvetica, sans-serif","'Arial Black', Gadget, sans-serif","Tahoma, Verdana, sans-serif","\"Times New Roman\", Times, serif","Verdana, Tahoma, sans-serif","\"Courier New\", Courier, monospace","'Roboto'"]}